backend_client/__init__.py
backend_client/api_client.py
backend_client/api_response.py
backend_client/configuration.py
backend_client/exceptions.py
backend_client/py.typed
backend_client/rest.py
backend_client/api/__init__.py
backend_client/api/lead_scraper_service_api.py
backend_client/models/__init__.py
backend_client/models/account.py
backend_client/models/any.py
backend_client/models/api_info.py
backend_client/models/auth_context.py
backend_client/models/auth_error_code.py
backend_client/models/authentication_error_message_response.py
backend_client/models/availability_info.py
backend_client/models/background_job_status.py
backend_client/models/bad_gateway_error_message_response.py
backend_client/models/conflict_error_message_response.py
backend_client/models/conflict_info.py
backend_client/models/create_account_request.py
backend_client/models/create_account_response.py
backend_client/models/create_scraping_job_request.py
backend_client/models/create_scraping_job_response.py
backend_client/models/delete_account_response.py
backend_client/models/delete_scraping_job_response.py
backend_client/models/dependency.py
backend_client/models/download_scraping_results_response.py
backend_client/models/error_response.py
backend_client/models/field_error.py
backend_client/models/field_violation.py
backend_client/models/forbidden_error_message_response.py
backend_client/models/gateway_timeout_error_message_response.py
backend_client/models/get_account_response.py
backend_client/models/get_scraping_job_response.py
backend_client/models/gone_error_message_response.py
backend_client/models/internal_error_code.py
backend_client/models/internal_error_message_response.py
backend_client/models/limit_info.py
backend_client/models/list_accounts_response.py
backend_client/models/list_scraping_jobs_response.py
backend_client/models/method_not_allowed_error_message_response.py
backend_client/models/mfa_info.py
backend_client/models/not_found_error_code.py
backend_client-1.11.23.dist-info/METADATA
backend_client-1.11.23.dist-info/WHEEL
backend_client-1.11.23.dist-info/top_level.txt
backend_client-1.11.23.dist-info/RECORD
